stretch/__init__.py
stretch/device.py
stretch/py.typed
stretch/trajectories.py
stretch/transport.py
stretch/motors/__init__.py
stretch/motors/stepper.py
stretch/scripts/__init__.py
stretch/scripts/teleop.py
stretch/uart/__init__.py
stretch/uart/cobbs_framing.py
stretch/uart/packing.py
stretch/uart/transport.py
stretch/utils/__init__.py
stretch/utils/colors.py
stretch/utils/config.py
stretch/utils/env.py
stretch/utils/formatting.py
stretch/utils/logging.py
stretch/utils/stats.py
stretch/utils/trajectories.py
super_simple_stretch_api-0.0.1.dist-info/METADATA
super_simple_stretch_api-0.0.1.dist-info/WHEEL
super_simple_stretch_api-0.0.1.dist-info/entry_points.txt
super_simple_stretch_api-0.0.1.dist-info/top_level.txt
super_simple_stretch_api-0.0.1.dist-info/RECORD
