Metadata-Version: 2.1
Name: super-simple-stretch-api
Version: 0.0.1
Summary: Super simple Python API for controlling the Stretch RE1 robot
Home-page: https://github.com/codekansas/super-simple-stretch-api
Author: Benjamin Bolte
Classifier: Development Status :: 4 - Beta
Classifier: Intended Audience :: Developers
Classifier: License :: OSI Approved :: MIT License
Classifier: Programming Language :: Python :: 3
Requires-Python: >=3.10
Requires-Dist: numpy
Requires-Dist: omegaconf
Requires-Dist: psutil
Requires-Dist: pyserial
Requires-Dist: pyyaml
Provides-Extra: dev
Requires-Dist: black ; extra == 'dev'
Requires-Dist: darglint ; extra == 'dev'
Requires-Dist: mypy ; extra == 'dev'
Requires-Dist: pytest ; extra == 'dev'
Requires-Dist: ruff ; extra == 'dev'
